bvi_aom/__init__.py
bvi_aom/main.py
bvi_aom-0.5.dist-info/METADATA
bvi_aom-0.5.dist-info/WHEEL
bvi_aom-0.5.dist-info/entry_points.txt
bvi_aom-0.5.dist-info/top_level.txt
bvi_aom-0.5.dist-info/RECORD
