Metadata-Version: 2.4
Name: bvi_aom
Version: 0.5
Requires-Dist: requests
Requires-Dist: tqdm
Dynamic: description
Dynamic: description-content-type
Dynamic: requires-dist
